memory_number_game/__init__.py
memory_number_game/__main__.py
memory_number_game/circle.py
memory_number_game/coordinate_generator.py
memory_number_game/game.py
memory_number_game/level.py
memory_number_game/load_config.py
memory_number_game-0.0.2.dist-info/METADATA
memory_number_game-0.0.2.dist-info/WHEEL
memory_number_game-0.0.2.dist-info/licenses/LICENSE
memory_number_game-0.0.2.dist-info/RECORD
