Metadata-Version: 2.3
Name: memory-number-game
Version: 0.0.2
Summary: A small exercise for me and a funny memory game!
Project-URL: Homepage, https://github.com/benji6892/number-game
Author-email: Benjain Walter <benjaminjwalter@gmail.com>
License-File: LICENSE
Requires-Python: >=3.8
